{
  "$ref": "#/definitions/blog",
  "definitions": {
    "blog": {
      "type": "object",
      "properties": {
        "title": {
          "type": "string"
        },
        "description": {
          "type": "string"
        },
        "date": {
          "type": "string"
        },
        "category": {
          "type": "string"
        },
        "readTime": {
          "type": "string"
        },
        "tags": {
          "type": "array",
          "items": {
            "type": "string"
          }
        },
        "author": {
          "type": "string"
        },
        "$schema": {
          "type": "string"
        }
      },
      "required": [
        "title",
        "description",
        "date",
        "category",
        "readTime"
      ],
      "additionalProperties": false
    }
  },
  "$schema": "http://json-schema.org/draft-07/schema#"
}